%CLASSFILE:Hello
%METHOD:<init>()V
%   0: aload_0[42](1)
p1_0_0(IV0,IV1,IM,OM,SP_INDEX,R) :-
         {INDEX_1 =0, VALUE = VALUE_1, SP_INDEX_NEW = SP_INDEX + 1, WRITE_INDEX = SP_INDEX + 1},
         read_0(INDEX_1,IV1,VALUE_1),
         write_0(WRITE_INDEX,IV1,W1,VALUE),
         p1_0_1(W0,W1,IM,OM,SP_INDEX_NEW,R).
%   1: invokespecial[183](3) 1
p1_0_1(IV0,IV1,IM,OM,SP_INDEX,R) :-
         {W0=IV1,},
, p0_0_0(,IM,OM,R)p1_0_2(IV0,R,IM,OM,R) 
%   4: return[177](1)
p1_0_2(IV0,IV1,IM,OM,SP_INDEX,R) :-
         {},

%READ AND WRITE PREDICATES OF:<init>()V
read_0(SP,IV0,IV1,IV0) :- {SP = 0}
read_0(SP,IV0,IV1,IV1) :- {SP = 1}
write_0(SP,IV0,IV1,W0,W1,VAL) :- {SP = 0,W0=VAL,W1=IV1}
write_0(SP,IV0,IV1,W0,W1,VAL) :- {SP = 1,W0=IV0,W1=VAL}
%END OF METHOD:<init>()V
%METHOD:main([Ljava/lang/String;)V
%   0: lconst_1[10](1)
p1_1_0(IV0,IV1,IV2,IV3,IV4,IV5,IV6,IV7,IV8,IM,OM,SP_INDEX,R) :-
         {VALUE = 1,SP_INDEX_NEW = SP_INDEX + 1, WRITE_INDEX = SP_INDEX + 1},
         write_1(WRITE_INDEX,IV1,IV2,IV3,IV4,IV5,IV6,IV7,IV8,W1,W2,W3,W4,W5,W6,W7,W8,VALUE),
         p1_1_1(W0,W1,W2,W3,W4,W5,W6,W7,W8,IM,OM,SP_INDEX_NEW,R).
%   1: lstore_1[64](1)
p1_1_1(IV0,IV1,IV2,IV3,IV4,IV5,IV6,IV7,IV8,IM,OM,SP_INDEX,R) :-
         {INDEX_1 = SP_INDEX,VALUE = VALUE_1 ,WRITE_INDEX = 1, SP_INDEX_NEW = SP_INDEX -1},
         read_1(INDEX_1,IV1,IV2,IV3,IV4,IV5,IV6,IV7,IV8,VALUE_1),
         write_1(WRITE_INDEX,IV1,IV2,IV3,IV4,IV5,IV6,IV7,IV8,W1,W2,W3,W4,W5,W6,W7,W8,VALUE),
         p1_1_2(W0,W1,W2,W3,W4,W5,W6,W7,W8,IM,OM,SP_INDEX_NEW,R).
%   2: ldc2_w[20](3) 2
p1_1_2(IV0,IV1,IV2,IV3,IV4,IV5,IV6,IV7,IV8,IM,OM,SP_INDEX,R) :-
         {VALUE = 6000.0,SP_INDEX_NEW = SP_INDEX + 1, WRITE_INDEX = SP_INDEX + 1},
         write_1(WRITE_INDEX,IV1,IV2,IV3,IV4,IV5,IV6,IV7,IV8,W1,W2,W3,W4,W5,W6,W7,W8,VALUE),
         p1_1_3(W0,W1,W2,W3,W4,W5,W6,W7,W8,IM,OM,SP_INDEX_NEW,R).
%   5: dstore_3[74](1)
p1_1_3(IV0,IV1,IV2,IV3,IV4,IV5,IV6,IV7,IV8,IM,OM,SP_INDEX,R) :-
         {INDEX_1 = SP_INDEX,VALUE = VALUE_1 ,WRITE_INDEX = 2, SP_INDEX_NEW = SP_INDEX -1},
         read_1(INDEX_1,IV1,IV2,IV3,IV4,IV5,IV6,IV7,IV8,VALUE_1),
         write_1(WRITE_INDEX,IV1,IV2,IV3,IV4,IV5,IV6,IV7,IV8,W1,W2,W3,W4,W5,W6,W7,W8,VALUE),
         p1_1_4(W0,W1,W2,W3,W4,W5,W6,W7,W8,IM,OM,SP_INDEX_NEW,R).
%   6: iconst_2[5](1)
p1_1_4(IV0,IV1,IV2,IV3,IV4,IV5,IV6,IV7,IV8,IM,OM,SP_INDEX,R) :-
         {VALUE = 2,SP_INDEX_NEW = SP_INDEX + 1, WRITE_INDEX = SP_INDEX + 1},
         write_1(WRITE_INDEX,IV1,IV2,IV3,IV4,IV5,IV6,IV7,IV8,W1,W2,W3,W4,W5,W6,W7,W8,VALUE),
         p1_1_5(W0,W1,W2,W3,W4,W5,W6,W7,W8,IM,OM,SP_INDEX_NEW,R).
%   7: istore[54](2) 5
p1_1_5(IV0,IV1,IV2,IV3,IV4,IV5,IV6,IV7,IV8,IM,OM,SP_INDEX,R) :-
         {INDEX_1 = SP_INDEX,VALUE = VALUE_1 ,WRITE_INDEX = 3, SP_INDEX_NEW = SP_INDEX -1},
         read_1(INDEX_1,IV1,IV2,IV3,IV4,IV5,IV6,IV7,IV8,VALUE_1),
         write_1(WRITE_INDEX,IV1,IV2,IV3,IV4,IV5,IV6,IV7,IV8,W1,W2,W3,W4,W5,W6,W7,W8,VALUE),
         p1_1_6(W0,W1,W2,W3,W4,W5,W6,W7,W8,IM,OM,SP_INDEX_NEW,R).
%   9: iconst_0[3](1)
p1_1_6(IV0,IV1,IV2,IV3,IV4,IV5,IV6,IV7,IV8,IM,OM,SP_INDEX,R) :-
         {VALUE = 0,SP_INDEX_NEW = SP_INDEX + 1, WRITE_INDEX = SP_INDEX + 1},
         write_1(WRITE_INDEX,IV1,IV2,IV3,IV4,IV5,IV6,IV7,IV8,W1,W2,W3,W4,W5,W6,W7,W8,VALUE),
         p1_1_7(W0,W1,W2,W3,W4,W5,W6,W7,W8,IM,OM,SP_INDEX_NEW,R).
%  10: istore[54](2) 6
p1_1_7(IV0,IV1,IV2,IV3,IV4,IV5,IV6,IV7,IV8,IM,OM,SP_INDEX,R) :-
         {INDEX_1 = SP_INDEX,VALUE = VALUE_1 ,WRITE_INDEX = 4, SP_INDEX_NEW = SP_INDEX -1},
         read_1(INDEX_1,IV1,IV2,IV3,IV4,IV5,IV6,IV7,IV8,VALUE_1),
         write_1(WRITE_INDEX,IV1,IV2,IV3,IV4,IV5,IV6,IV7,IV8,W1,W2,W3,W4,W5,W6,W7,W8,VALUE),
         p1_1_8(W0,W1,W2,W3,W4,W5,W6,W7,W8,IM,OM,SP_INDEX_NEW,R).
%  12: iload[21](2) 6
p1_1_8(IV0,IV1,IV2,IV3,IV4,IV5,IV6,IV7,IV8,IM,OM,SP_INDEX,R) :-
         {INDEX_1 =4, VALUE = VALUE_1, SP_INDEX_NEW = SP_INDEX + 1, WRITE_INDEX = SP_INDEX + 1},
         read_1(INDEX_1,IV1,IV2,IV3,IV4,IV5,IV6,IV7,IV8,VALUE_1),
         write_1(WRITE_INDEX,IV1,IV2,IV3,IV4,IV5,IV6,IV7,IV8,W1,W2,W3,W4,W5,W6,W7,W8,VALUE),
         p1_1_9(W0,W1,W2,W3,W4,W5,W6,W7,W8,IM,OM,SP_INDEX_NEW,R).
%  14: iload[21](2) 5
p1_1_9(IV0,IV1,IV2,IV3,IV4,IV5,IV6,IV7,IV8,IM,OM,SP_INDEX,R) :-
         {INDEX_1 =3, VALUE = VALUE_1, SP_INDEX_NEW = SP_INDEX + 1, WRITE_INDEX = SP_INDEX + 1},
         read_1(INDEX_1,IV1,IV2,IV3,IV4,IV5,IV6,IV7,IV8,VALUE_1),
         write_1(WRITE_INDEX,IV1,IV2,IV3,IV4,IV5,IV6,IV7,IV8,W1,W2,W3,W4,W5,W6,W7,W8,VALUE),
         p1_1_10(W0,W1,W2,W3,W4,W5,W6,W7,W8,IM,OM,SP_INDEX_NEW,R).
%  16: if_icmpge[162](3) -> 52
p1_1_10(IV0,IV1,IV2,IV3,IV4,IV5,IV6,IV7,IV8,IM,OM,SP_INDEX,R) :- 
         {INDEX_1 = SP_INDEX, INDEX_2 = SP_INDEX -1,SP_INDEX_NEW = SP_INDEX -2, VALUE_2 < VALUE_1}
         read_1(INDEX_1,IV1,IV2,IV3,IV4,IV5,IV6,IV7,IV8,VALUE_1),
         read_1(INDEX_2,IV1,IV2,IV3,IV4,IV5,IV6,IV7,IV8,VALUE_2),
         p1_1_11(W0,W1,W2,W3,W4,W5,W6,W7,W8,IM,OM,SP_INDEX_NEW,R)..
p1_1_10(IV0,IV1,IV2,IV3,IV4,IV5,IV6,IV7,IV8,IM,OM,SP_INDEX,R) :- 
         {INDEX_1 = SP_INDEX, INDEX_2 = SP_INDEX -1,SP_INDEX_NEW = SP_INDEX -2, VALUE2 => VALUE_1}
         read_1(INDEX_1,IV1,IV2,IV3,IV4,IV5,IV6,IV7,IV8,VALUE_1),
         read_1(INDEX_2,IV1,IV2,IV3,IV4,IV5,IV6,IV7,IV8,VALUE_2),
         p1_1_31(W0,W1,W2,W3,W4,W5,W6,W7,W8,IM,OM,SP_INDEX_NEW,R)
%  19: dload_3[41](1)
p1_1_11(IV0,IV1,IV2,IV3,IV4,IV5,IV6,IV7,IV8,IM,OM,SP_INDEX,R) :-
         {INDEX_1 =2, VALUE = VALUE_1, SP_INDEX_NEW = SP_INDEX + 1, WRITE_INDEX = SP_INDEX + 1},
         read_1(INDEX_1,IV1,IV2,IV3,IV4,IV5,IV6,IV7,IV8,VALUE_1),
         write_1(WRITE_INDEX,IV1,IV2,IV3,IV4,IV5,IV6,IV7,IV8,W1,W2,W3,W4,W5,W6,W7,W8,VALUE),
         p1_1_12(W0,W1,W2,W3,W4,W5,W6,W7,W8,IM,OM,SP_INDEX_NEW,R).
%  20: ldc2_w[20](3) 2
p1_1_12(IV0,IV1,IV2,IV3,IV4,IV5,IV6,IV7,IV8,IM,OM,SP_INDEX,R) :-
         {VALUE = 6000.0,SP_INDEX_NEW = SP_INDEX + 1, WRITE_INDEX = SP_INDEX + 1},
         write_1(WRITE_INDEX,IV1,IV2,IV3,IV4,IV5,IV6,IV7,IV8,W1,W2,W3,W4,W5,W6,W7,W8,VALUE),
         p1_1_13(W0,W1,W2,W3,W4,W5,W6,W7,W8,IM,OM,SP_INDEX_NEW,R).
%  23: dcmpl[151](1)
p1_1_13(IV0,IV1,IV2,IV3,IV4,IV5,IV6,IV7,IV8,IM,OM,SP_INDEX,R) :- 
         {INDEX_1 = SP_INDEX, INDEX_2 = SP_INDEX -1,SP_INDEX_NEW = SP_INDEX -1, WRITE_INDEX = SP_INDEX -1, VALUE_2 > VALUE_1, VALUE = 1}
         read_1(INDEX_1,IV1,IV2,IV3,IV4,IV5,IV6,IV7,IV8,VALUE_1),
         read_1(INDEX_2,IV1,IV2,IV3,IV4,IV5,IV6,IV7,IV8,VALUE_2),
         write_1(WRITE_INDEX,IV1,IV2,IV3,IV4,IV5,IV6,IV7,IV8,W1,W2,W3,W4,W5,W6,W7,W8,VALUE),
,         p1_1_14(W0,W1,W2,W3,W4,W5,W6,W7,W8,IM,OM,SP_INDEX_NEW,R).
p1_1_13(IV0,IV1,IV2,IV3,IV4,IV5,IV6,IV7,IV8,IM,OM,SP_INDEX,R) :- 
         {INDEX_1 = SP_INDEX, INDEX_2 = SP_INDEX -1,SP_INDEX_NEW = SP_INDEX -1, WRITE_INDEX = SP_INDEX -1, VALUE_2 = VALUE_1, VALUE = 0}
         read_1(INDEX_1,IV1,IV2,IV3,IV4,IV5,IV6,IV7,IV8,VALUE_1),
         read_1(INDEX_2,IV1,IV2,IV3,IV4,IV5,IV6,IV7,IV8,VALUE_2),
         write_1(WRITE_INDEX,IV1,IV2,IV3,IV4,IV5,IV6,IV7,IV8,W1,W2,W3,W4,W5,W6,W7,W8,VALUE),
,         p1_1_14(W0,W1,W2,W3,W4,W5,W6,W7,W8,IM,OM,SP_INDEX_NEW,R).
p1_1_13(IV0,IV1,IV2,IV3,IV4,IV5,IV6,IV7,IV8,IM,OM,SP_INDEX,R) :- 
         {INDEX_1 = SP_INDEX, INDEX_2 = SP_INDEX -1,SP_INDEX_NEW = SP_INDEX -1, WRITE_INDEX = SP_INDEX -1, VALUE_2 < VALUE_1, VALUE = -1}
         read_1(INDEX_1,IV1,IV2,IV3,IV4,IV5,IV6,IV7,IV8,VALUE_1),
         read_1(INDEX_2,IV1,IV2,IV3,IV4,IV5,IV6,IV7,IV8,VALUE_2),
         write_1(WRITE_INDEX,IV1,IV2,IV3,IV4,IV5,IV6,IV7,IV8,W1,W2,W3,W4,W5,W6,W7,W8,VALUE),
,         p1_1_14(W0,W1,W2,W3,W4,W5,W6,W7,W8,IM,OM,SP_INDEX_NEW,R).
p1_1_13(IV0,IV1,IV2,IV3,IV4,IV5,IV6,IV7,IV8,IM,OM,SP_INDEX,R) :- 
         {INDEX_1 = SP_INDEX, INDEX_2 = SP_INDEX -1,SP_INDEX_NEW = SP_INDEX -1, WRITE_INDEX = SP_INDEX -1, VALUE_2 = nan,VALUE = -1}
         read_1(INDEX_1,IV1,IV2,IV3,IV4,IV5,IV6,IV7,IV8,VALUE_1),
         read_1(INDEX_2,IV1,IV2,IV3,IV4,IV5,IV6,IV7,IV8,VALUE_2),
         write_1(WRITE_INDEX,IV1,IV2,IV3,IV4,IV5,IV6,IV7,IV8,W1,W2,W3,W4,W5,W6,W7,W8,VALUE),
,         p1_1_14(W0,W1,W2,W3,W4,W5,W6,W7,W8,IM,OM,SP_INDEX_NEW,R).
p1_1_13(IV0,IV1,IV2,IV3,IV4,IV5,IV6,IV7,IV8,IM,OM,SP_INDEX,R) :- 
         {INDEX_1 = SP_INDEX, INDEX_2 = SP_INDEX -1,SP_INDEX_NEW = SP_INDEX -1, WRITE_INDEX = SP_INDEX -1, VALUE_1 = nan,VALUE_1 = - 1}
         read_1(INDEX_1,IV1,IV2,IV3,IV4,IV5,IV6,IV7,IV8,VALUE_1),
         read_1(INDEX_2,IV1,IV2,IV3,IV4,IV5,IV6,IV7,IV8,VALUE_2),
         write_1(WRITE_INDEX,IV1,IV2,IV3,IV4,IV5,IV6,IV7,IV8,W1,W2,W3,W4,W5,W6,W7,W8,VALUE),
,         p1_1_14(W0,W1,W2,W3,W4,W5,W6,W7,W8,IM,OM,SP_INDEX_NEW,R).
%  24: ifne[154](3) -> 36
p1_1_14(IV0,IV1,IV2,IV3,IV4,IV5,IV6,IV7,IV8,IM,OM,SP_INDEX,R) :- 
         {INDEX_1 = SP_INDEX,SP_INDEX_NEW = SP_INDEX -1, VALUE_1 = 0}
         read_1(INDEX_1,IV1,IV2,IV3,IV4,IV5,IV6,IV7,IV8,VALUE_1),
         read_1(INDEX_2,IV1,IV2,IV3,IV4,IV5,IV6,IV7,IV8,VALUE_2),
         p1_1_15(W0,W1,W2,W3,W4,W5,W6,W7,W8,IM,OM,SP_INDEX_NEW,R)..
p1_1_14(IV0,IV1,IV2,IV3,IV4,IV5,IV6,IV7,IV8,IM,OM,SP_INDEX,R) :- 
         {INDEX_1 = SP_INDEX,SP_INDEX_NEW = SP_INDEX -1, VALUE_1 =\= 0}
         read_1(INDEX_1,IV1,IV2,IV3,IV4,IV5,IV6,IV7,IV8,VALUE_1),
         read_1(INDEX_2,IV1,IV2,IV3,IV4,IV5,IV6,IV7,IV8,VALUE_2),
         p1_1_21(W0,W1,W2,W3,W4,W5,W6,W7,W8,IM,OM,SP_INDEX_NEW,R)
%  27: dload_3[41](1)
p1_1_15(IV0,IV1,IV2,IV3,IV4,IV5,IV6,IV7,IV8,IM,OM,SP_INDEX,R) :-
         {INDEX_1 =2, VALUE = VALUE_1, SP_INDEX_NEW = SP_INDEX + 1, WRITE_INDEX = SP_INDEX + 1},
         read_1(INDEX_1,IV1,IV2,IV3,IV4,IV5,IV6,IV7,IV8,VALUE_1),
         write_1(WRITE_INDEX,IV1,IV2,IV3,IV4,IV5,IV6,IV7,IV8,W1,W2,W3,W4,W5,W6,W7,W8,VALUE),
         p1_1_16(W0,W1,W2,W3,W4,W5,W6,W7,W8,IM,OM,SP_INDEX_NEW,R).
%  28: iload[21](2) 5
p1_1_16(IV0,IV1,IV2,IV3,IV4,IV5,IV6,IV7,IV8,IM,OM,SP_INDEX,R) :-
         {INDEX_1 =3, VALUE = VALUE_1, SP_INDEX_NEW = SP_INDEX + 1, WRITE_INDEX = SP_INDEX + 1},
         read_1(INDEX_1,IV1,IV2,IV3,IV4,IV5,IV6,IV7,IV8,VALUE_1),
         write_1(WRITE_INDEX,IV1,IV2,IV3,IV4,IV5,IV6,IV7,IV8,W1,W2,W3,W4,W5,W6,W7,W8,VALUE),
         p1_1_17(W0,W1,W2,W3,W4,W5,W6,W7,W8,IM,OM,SP_INDEX_NEW,R).
%  30: i2d[135](1)
p1_1_17(IV0,IV1,IV2,IV3,IV4,IV5,IV6,IV7,IV8,IM,OM,SP_INDEX,R) :-
         {},
         p1_1_18(IV0,IV1,IV2,IV3,IV4,IV5,IV6,IV7,IV8,IM,OM,SP_INDEX,R)
%  31: ddiv[111](1)
p1_1_18(IV0,IV1,IV2,IV3,IV4,IV5,IV6,IV7,IV8,IM,OM,SP_INDEX,R) :-
         {INDEX_1 = SP_INDEX, INDEX_2 = SP_INDEX - 1, VALUE = VALUE_1 / VALUE_2, SP_INDEX_NEW = SP_INDEX -1, WRITE_INDEX = SP_INDEX -1},
         read_1(INDEX_1,IV1,IV2,IV3,IV4,IV5,IV6,IV7,IV8,VALUE_1),
         read_1(INDEX_2,IV1,IV2,IV3,IV4,IV5,IV6,IV7,IV8,VALUE_2),
         write_1(WRITE_INDEX,IV1,IV2,IV3,IV4,IV5,IV6,IV7,IV8,W1,W2,W3,W4,W5,W6,W7,W8,VALUE),
         p1_1_19(W0,W1,W2,W3,W4,W5,W6,W7,W8,IM,OM,SP_INDEX_NEW,R).
%  32: dstore_3[74](1)
p1_1_19(IV0,IV1,IV2,IV3,IV4,IV5,IV6,IV7,IV8,IM,OM,SP_INDEX,R) :-
         {INDEX_1 = SP_INDEX,VALUE = VALUE_1 ,WRITE_INDEX = 2, SP_INDEX_NEW = SP_INDEX -1},
         read_1(INDEX_1,IV1,IV2,IV3,IV4,IV5,IV6,IV7,IV8,VALUE_1),
         write_1(WRITE_INDEX,IV1,IV2,IV3,IV4,IV5,IV6,IV7,IV8,W1,W2,W3,W4,W5,W6,W7,W8,VALUE),
         p1_1_20(W0,W1,W2,W3,W4,W5,W6,W7,W8,IM,OM,SP_INDEX_NEW,R).
%  33: goto[167](3) -> 42
p1_1_20(IV0,IV1,IV2,IV3,IV4,IV5,IV6,IV7,IV8,IM,OM,SP_INDEX,R) :- 
         {}
         p1_1_25(IV0,IV1,IV2,IV3,IV4,IV5,IV6,IV7,IV8,IM,OM,SP_INDEX,R)
%  36: lload_1[31](1)
p1_1_21(IV0,IV1,IV2,IV3,IV4,IV5,IV6,IV7,IV8,IM,OM,SP_INDEX,R) :-
         {INDEX_1 =1, VALUE = VALUE_1, SP_INDEX_NEW = SP_INDEX + 1, WRITE_INDEX = SP_INDEX + 1},
         read_1(INDEX_1,IV1,IV2,IV3,IV4,IV5,IV6,IV7,IV8,VALUE_1),
         write_1(WRITE_INDEX,IV1,IV2,IV3,IV4,IV5,IV6,IV7,IV8,W1,W2,W3,W4,W5,W6,W7,W8,VALUE),
         p1_1_22(W0,W1,W2,W3,W4,W5,W6,W7,W8,IM,OM,SP_INDEX_NEW,R).
%  37: ldc2_w[20](3) 4
p1_1_22(IV0,IV1,IV2,IV3,IV4,IV5,IV6,IV7,IV8,IM,OM,SP_INDEX,R) :-
         {VALUE = 9,SP_INDEX_NEW = SP_INDEX + 1, WRITE_INDEX = SP_INDEX + 1},
         write_1(WRITE_INDEX,IV1,IV2,IV3,IV4,IV5,IV6,IV7,IV8,W1,W2,W3,W4,W5,W6,W7,W8,VALUE),
         p1_1_23(W0,W1,W2,W3,W4,W5,W6,W7,W8,IM,OM,SP_INDEX_NEW,R).
%  40: ladd[97](1)
p1_1_23(IV0,IV1,IV2,IV3,IV4,IV5,IV6,IV7,IV8,IM,OM,SP_INDEX,R) :-
         {INDEX_1 = SP_INDEX, INDEX_2 = SP_INDEX - 1, VALUE = VALUE_1 + VALUE_2, SP_INDEX_NEW = SP_INDEX -1, WRITE_INDEX = SP_INDEX -1},
         read_1(INDEX_1,IV1,IV2,IV3,IV4,IV5,IV6,IV7,IV8,VALUE_1),
         read_1(INDEX_2,IV1,IV2,IV3,IV4,IV5,IV6,IV7,IV8,VALUE_2),
         write_1(WRITE_INDEX,IV1,IV2,IV3,IV4,IV5,IV6,IV7,IV8,W1,W2,W3,W4,W5,W6,W7,W8,VALUE),
         p1_1_24(W0,W1,W2,W3,W4,W5,W6,W7,W8,IM,OM,SP_INDEX_NEW,R).
%  41: lstore_1[64](1)
p1_1_24(IV0,IV1,IV2,IV3,IV4,IV5,IV6,IV7,IV8,IM,OM,SP_INDEX,R) :-
         {INDEX_1 = SP_INDEX,VALUE = VALUE_1 ,WRITE_INDEX = 1, SP_INDEX_NEW = SP_INDEX -1},
         read_1(INDEX_1,IV1,IV2,IV3,IV4,IV5,IV6,IV7,IV8,VALUE_1),
         write_1(WRITE_INDEX,IV1,IV2,IV3,IV4,IV5,IV6,IV7,IV8,W1,W2,W3,W4,W5,W6,W7,W8,VALUE),
         p1_1_25(W0,W1,W2,W3,W4,W5,W6,W7,W8,IM,OM,SP_INDEX_NEW,R).
%  42: iload[21](2) 6
p1_1_25(IV0,IV1,IV2,IV3,IV4,IV5,IV6,IV7,IV8,IM,OM,SP_INDEX,R) :-
         {INDEX_1 =4, VALUE = VALUE_1, SP_INDEX_NEW = SP_INDEX + 1, WRITE_INDEX = SP_INDEX + 1},
         read_1(INDEX_1,IV1,IV2,IV3,IV4,IV5,IV6,IV7,IV8,VALUE_1),
         write_1(WRITE_INDEX,IV1,IV2,IV3,IV4,IV5,IV6,IV7,IV8,W1,W2,W3,W4,W5,W6,W7,W8,VALUE),
         p1_1_26(W0,W1,W2,W3,W4,W5,W6,W7,W8,IM,OM,SP_INDEX_NEW,R).
%  44: iconst_1[4](1)
p1_1_26(IV0,IV1,IV2,IV3,IV4,IV5,IV6,IV7,IV8,IM,OM,SP_INDEX,R) :-
         {VALUE = 1,SP_INDEX_NEW = SP_INDEX + 1, WRITE_INDEX = SP_INDEX + 1},
         write_1(WRITE_INDEX,IV1,IV2,IV3,IV4,IV5,IV6,IV7,IV8,W1,W2,W3,W4,W5,W6,W7,W8,VALUE),
         p1_1_27(W0,W1,W2,W3,W4,W5,W6,W7,W8,IM,OM,SP_INDEX_NEW,R).
%  45: iadd[96](1)
p1_1_27(IV0,IV1,IV2,IV3,IV4,IV5,IV6,IV7,IV8,IM,OM,SP_INDEX,R) :-
         {INDEX_1 = SP_INDEX, INDEX_2 = SP_INDEX - 1, VALUE = VALUE_1 + VALUE_2, SP_INDEX_NEW = SP_INDEX -1, WRITE_INDEX = SP_INDEX -1},
         read_1(INDEX_1,IV1,IV2,IV3,IV4,IV5,IV6,IV7,IV8,VALUE_1),
         read_1(INDEX_2,IV1,IV2,IV3,IV4,IV5,IV6,IV7,IV8,VALUE_2),
         write_1(WRITE_INDEX,IV1,IV2,IV3,IV4,IV5,IV6,IV7,IV8,W1,W2,W3,W4,W5,W6,W7,W8,VALUE),
         p1_1_28(W0,W1,W2,W3,W4,W5,W6,W7,W8,IM,OM,SP_INDEX_NEW,R).
%  46: i2s[147](1)
p1_1_28(IV0,IV1,IV2,IV3,IV4,IV5,IV6,IV7,IV8,IM,OM,SP_INDEX,R) :-
         {},
         p1_1_29(IV0,IV1,IV2,IV3,IV4,IV5,IV6,IV7,IV8,IM,OM,SP_INDEX,R)
%  47: istore[54](2) 6
p1_1_29(IV0,IV1,IV2,IV3,IV4,IV5,IV6,IV7,IV8,IM,OM,SP_INDEX,R) :-
         {INDEX_1 = SP_INDEX,VALUE = VALUE_1 ,WRITE_INDEX = 4, SP_INDEX_NEW = SP_INDEX -1},
         read_1(INDEX_1,IV1,IV2,IV3,IV4,IV5,IV6,IV7,IV8,VALUE_1),
         write_1(WRITE_INDEX,IV1,IV2,IV3,IV4,IV5,IV6,IV7,IV8,W1,W2,W3,W4,W5,W6,W7,W8,VALUE),
         p1_1_30(W0,W1,W2,W3,W4,W5,W6,W7,W8,IM,OM,SP_INDEX_NEW,R).
%  49: goto[167](3) -> 12
p1_1_30(IV0,IV1,IV2,IV3,IV4,IV5,IV6,IV7,IV8,IM,OM,SP_INDEX,R) :- 
         {}
         p1_1_8(IV0,IV1,IV2,IV3,IV4,IV5,IV6,IV7,IV8,IM,OM,SP_INDEX,R)
%  52: iload[21](2) 5
p1_1_31(IV0,IV1,IV2,IV3,IV4,IV5,IV6,IV7,IV8,IM,OM,SP_INDEX,R) :-
         {INDEX_1 =3, VALUE = VALUE_1, SP_INDEX_NEW = SP_INDEX + 1, WRITE_INDEX = SP_INDEX + 1},
         read_1(INDEX_1,IV1,IV2,IV3,IV4,IV5,IV6,IV7,IV8,VALUE_1),
         write_1(WRITE_INDEX,IV1,IV2,IV3,IV4,IV5,IV6,IV7,IV8,W1,W2,W3,W4,W5,W6,W7,W8,VALUE),
         p1_1_32(W0,W1,W2,W3,W4,W5,W6,W7,W8,IM,OM,SP_INDEX_NEW,R).
%  54: ineg[116](1)
p1_1_32(IV0,IV1,IV2,IV3,IV4,IV5,IV6,IV7,IV8,IM,OM,SP_INDEX,R) :-
         {INDEX_1 = SP_INDEX, VALUE = 0 - VALUE_1, WRITE_INDEX = SP_INDEX, SP_INDEX_NEW = SP_INDEX},
         read_1(INDEX_1,IV1,IV2,IV3,IV4,IV5,IV6,IV7,IV8,VALUE_1),
         write_1(WRITE_INDEX,IV1,IV2,IV3,IV4,IV5,IV6,IV7,IV8,W1,W2,W3,W4,W5,W6,W7,W8,VALUE),
         p1_1_33(W0,W1,W2,W3,W4,W5,W6,W7,W8,IM,OM,SP_INDEX_NEW,R).
%  55: istore[54](2) 5
p1_1_33(IV0,IV1,IV2,IV3,IV4,IV5,IV6,IV7,IV8,IM,OM,SP_INDEX,R) :-
         {INDEX_1 = SP_INDEX,VALUE = VALUE_1 ,WRITE_INDEX = 3, SP_INDEX_NEW = SP_INDEX -1},
         read_1(INDEX_1,IV1,IV2,IV3,IV4,IV5,IV6,IV7,IV8,VALUE_1),
         write_1(WRITE_INDEX,IV1,IV2,IV3,IV4,IV5,IV6,IV7,IV8,W1,W2,W3,W4,W5,W6,W7,W8,VALUE),
         p1_1_34(W0,W1,W2,W3,W4,W5,W6,W7,W8,IM,OM,SP_INDEX_NEW,R).
%  57: return[177](1)
p1_1_34(IV0,IV1,IV2,IV3,IV4,IV5,IV6,IV7,IV8,IM,OM,SP_INDEX,R) :-
         {},

%READ AND WRITE PREDICATES OF:main([Ljava/lang/String;)V
read_1(SP,IV0,IV1,IV2,IV3,IV4,IV5,IV6,IV7,IV8,IV0) :- {SP = 0}
read_1(SP,IV0,IV1,IV2,IV3,IV4,IV5,IV6,IV7,IV8,IV1) :- {SP = 1}
read_1(SP,IV0,IV1,IV2,IV3,IV4,IV5,IV6,IV7,IV8,IV2) :- {SP = 2}
read_1(SP,IV0,IV1,IV2,IV3,IV4,IV5,IV6,IV7,IV8,IV3) :- {SP = 3}
read_1(SP,IV0,IV1,IV2,IV3,IV4,IV5,IV6,IV7,IV8,IV4) :- {SP = 4}
read_1(SP,IV0,IV1,IV2,IV3,IV4,IV5,IV6,IV7,IV8,IV5) :- {SP = 5}
read_1(SP,IV0,IV1,IV2,IV3,IV4,IV5,IV6,IV7,IV8,IV6) :- {SP = 6}
read_1(SP,IV0,IV1,IV2,IV3,IV4,IV5,IV6,IV7,IV8,IV7) :- {SP = 7}
read_1(SP,IV0,IV1,IV2,IV3,IV4,IV5,IV6,IV7,IV8,IV8) :- {SP = 8}
write_1(SP,IV0,IV1,IV2,IV3,IV4,IV5,IV6,IV7,IV8,W0,W1,W2,W3,W4,W5,W6,W7,W8,VAL) :- {SP = 0,W0=VAL,W1=IV1,W2=IV2,W3=IV3,W4=IV4,W5=IV5,W6=IV6,W7=IV7,W8=IV8}
write_1(SP,IV0,IV1,IV2,IV3,IV4,IV5,IV6,IV7,IV8,W0,W1,W2,W3,W4,W5,W6,W7,W8,VAL) :- {SP = 1,W0=IV0,W1=VAL,W2=IV2,W3=IV3,W4=IV4,W5=IV5,W6=IV6,W7=IV7,W8=IV8}
write_1(SP,IV0,IV1,IV2,IV3,IV4,IV5,IV6,IV7,IV8,W0,W1,W2,W3,W4,W5,W6,W7,W8,VAL) :- {SP = 2,W0=IV0,W1=IV1,W2=VAL,W3=IV3,W4=IV4,W5=IV5,W6=IV6,W7=IV7,W8=IV8}
write_1(SP,IV0,IV1,IV2,IV3,IV4,IV5,IV6,IV7,IV8,W0,W1,W2,W3,W4,W5,W6,W7,W8,VAL) :- {SP = 3,W0=IV0,W1=IV1,W2=IV2,W3=VAL,W4=IV4,W5=IV5,W6=IV6,W7=IV7,W8=IV8}
write_1(SP,IV0,IV1,IV2,IV3,IV4,IV5,IV6,IV7,IV8,W0,W1,W2,W3,W4,W5,W6,W7,W8,VAL) :- {SP = 4,W0=IV0,W1=IV1,W2=IV2,W3=IV3,W4=VAL,W5=IV5,W6=IV6,W7=IV7,W8=IV8}
write_1(SP,IV0,IV1,IV2,IV3,IV4,IV5,IV6,IV7,IV8,W0,W1,W2,W3,W4,W5,W6,W7,W8,VAL) :- {SP = 5,W0=IV0,W1=IV1,W2=IV2,W3=IV3,W4=IV4,W5=VAL,W6=IV6,W7=IV7,W8=IV8}
write_1(SP,IV0,IV1,IV2,IV3,IV4,IV5,IV6,IV7,IV8,W0,W1,W2,W3,W4,W5,W6,W7,W8,VAL) :- {SP = 6,W0=IV0,W1=IV1,W2=IV2,W3=IV3,W4=IV4,W5=IV5,W6=VAL,W7=IV7,W8=IV8}
write_1(SP,IV0,IV1,IV2,IV3,IV4,IV5,IV6,IV7,IV8,W0,W1,W2,W3,W4,W5,W6,W7,W8,VAL) :- {SP = 7,W0=IV0,W1=IV1,W2=IV2,W3=IV3,W4=IV4,W5=IV5,W6=IV6,W7=VAL,W8=IV8}
write_1(SP,IV0,IV1,IV2,IV3,IV4,IV5,IV6,IV7,IV8,W0,W1,W2,W3,W4,W5,W6,W7,W8,VAL) :- {SP = 8,W0=IV0,W1=IV1,W2=IV2,W3=IV3,W4=IV4,W5=IV5,W6=IV6,W7=IV7,W8=VAL}
%END OF METHOD:main([Ljava/lang/String;)V



